timeago/__init__.py
timeago/excepts.py
timeago/parser.py
timeago/setting.py
timeago/locales/__init__.py
timeago/locales/bg.py
timeago/locales/ca.py
timeago/locales/create_tests.py
timeago/locales/da.py
timeago/locales/de.py
timeago/locales/el.py
timeago/locales/en.py
timeago/locales/en_short.py
timeago/locales/es.py
timeago/locales/eu.py
timeago/locales/fa_IR.py
timeago/locales/fi.py
timeago/locales/fr.py
timeago/locales/gl.py
timeago/locales/he.py
timeago/locales/hu.py
timeago/locales/import_locale.py
timeago/locales/in_BG.py
timeago/locales/in_HI.py
timeago/locales/in_ID.py
timeago/locales/it.py
timeago/locales/ja.py
timeago/locales/ko.py
timeago/locales/ml.py
timeago/locales/my.py
timeago/locales/nb_NO.py
timeago/locales/nl.py
timeago/locales/nn_NO.py
timeago/locales/pl.py
timeago/locales/pt_BR.py
timeago/locales/ru.py
timeago/locales/sv_SE.py
timeago/locales/ta.py
timeago/locales/th.py
timeago/locales/tr.py
timeago/locales/vi.py
timeago/locales/zh_CN.py
timeago/locales/zh_TW.py
timeago-1.0.10.dist-info/LICENSE
timeago-1.0.10.dist-info/METADATA
timeago-1.0.10.dist-info/WHEEL
timeago-1.0.10.dist-info/top_level.txt
timeago-1.0.10.dist-info/RECORD
